{
  "version":"1.0",
  "externalPublication":false,
  "approval":"OWNER_REVIEW_REQUIRED",
  "assetRule":"Only public-safe media with documented rights and privacy review may be attached.",
  "posts":[
    {"day":1,"theme":"Problem clarity","draft":"One messy problem becomes facts, gaps, risks, and five next actions.","platforms":["Facebook","Instagram","LinkedIn"],"asset":"PUBLIC_SAFE_ASSET_REQUIRED","publishAllowed":false},
    {"day":2,"theme":"Free tool","draft":"Run a planning calculator before buying work.","platforms":["Facebook","Instagram","LinkedIn"],"asset":"FREE_TOOL_SCREENSHOT_REQUIRED","publishAllowed":false},
    {"day":3,"theme":"Automation payback","draft":"A payback estimate is only as good as uptime, labor, quality, maintenance, and risk assumptions.","platforms":["LinkedIn","YouTube"],"asset":"PUBLIC_SAFE_DIAGRAM_REQUIRED","publishAllowed":false},
    {"day":4,"theme":"Shop improvement","draft":"Separate active-job staging from long-term storage before buying more cabinets.","platforms":["Facebook","Instagram","LinkedIn"],"asset":"PUBLIC_SAFE_LAYOUT_REQUIRED","publishAllowed":false},
    {"day":5,"theme":"Proof boundaries","draft":"Good proof labels what is historical, reconstructed, demonstrated, and still private.","platforms":["Facebook","Instagram","LinkedIn","Google Business Profile"],"asset":"CLASSIFIED_PROOF_CARD_REQUIRED","publishAllowed":false},
    {"day":6,"theme":"Product scope","draft":"Fixed deliverables and bounded revisions protect both customer and business.","platforms":["Facebook","Instagram","LinkedIn"],"asset":"PRODUCT_SCOPE_CARD_REQUIRED","publishAllowed":false},
    {"day":7,"theme":"Business OS control","draft":"Selected-record approval prevents one decision from becoming an accidental bulk action.","platforms":["LinkedIn","YouTube"],"asset":"PORTAL_DEMO_REQUIRED","publishAllowed":false},
    {"day":8,"theme":"Business Concept Builder","draft":"A rough idea can become segments, offers, SOPs, a sitemap, a launch plan, and Tasks.","platforms":["Facebook","Instagram","LinkedIn"],"asset":"BUILDER_DEMO_REQUIRED","publishAllowed":false},
    {"day":9,"theme":"Residential planning","draft":"Measure fixed obstacles and protect the main traffic lane before choosing storage.","platforms":["Facebook","Instagram","Google Business Profile"],"asset":"PUBLIC_SAFE_LAYOUT_REQUIRED","publishAllowed":false},
    {"day":10,"theme":"Vendor RFQ","draft":"A complete quote defines scope, interfaces, acceptance, exclusions, lead time, training, and warranty.","platforms":["LinkedIn","YouTube"],"asset":"CHECKLIST_PREVIEW_REQUIRED","publishAllowed":false},
    {"day":11,"theme":"Problem Snapshot","draft":"Clarity is a product: one defined issue, one practical first move, and no pressure to buy a larger build.","platforms":["Facebook","Instagram","LinkedIn"],"asset":"H38_P001_CARD_REQUIRED","publishAllowed":false},
    {"day":12,"theme":"Machining tool","draft":"RPM and feed calculations are a starting point, not a substitute for toolmaker and machine limits.","platforms":["LinkedIn","YouTube"],"asset":"MACHINING_TOOL_SCREENSHOT_REQUIRED","publishAllowed":false},
    {"day":13,"theme":"Bottleneck cost","draft":"Minutes lost every day become real annual hours and cost.","platforms":["Facebook","Instagram","LinkedIn"],"asset":"BOTTLENECK_TOOL_SCREENSHOT_REQUIRED","publishAllowed":false},
    {"day":14,"theme":"Quote completeness","draft":"Price is only one part of a usable vendor quote.","platforms":["LinkedIn","Google Business Profile"],"asset":"QUOTE_CHECKLIST_REQUIRED","publishAllowed":false},
    {"day":15,"theme":"Anonymized reconstruction","draft":"A reconstruction can teach the process without exposing employers, customers, vendors, drawings, or part data.","platforms":["LinkedIn","YouTube"],"asset":"ANONYMIZED_PROOF_REQUIRED","publishAllowed":false},
    {"day":16,"theme":"Layout inputs","draft":"Doors, windows, fixed obstacles, utilities, traffic, and must-keep items come before layout advice.","platforms":["Facebook","Instagram","Google Business Profile"],"asset":"LAYOUT_INPUT_CARD_REQUIRED","publishAllowed":false},
    {"day":17,"theme":"Owner approval","draft":"Automation should remove repetition without removing the owner's decision authority.","platforms":["LinkedIn","YouTube"],"asset":"APPROVAL_FLOW_REQUIRED","publishAllowed":false},
    {"day":18,"theme":"Care plans","draft":"Recurring support must define included requests, response time, exclusions, rollover, and cancellation.","platforms":["Facebook","Instagram","LinkedIn"],"asset":"CARE_PLAN_CARD_REQUIRED","publishAllowed":false},
    {"day":19,"theme":"Bar-feed calculator","draft":"Usable bar length, cutoff allowance, remnant, cycle time, and efficiency control the estimate.","platforms":["LinkedIn","YouTube"],"asset":"BAR_FEED_TOOL_REQUIRED","publishAllowed":false},
    {"day":20,"theme":"Press-feed worksheet","draft":"Theoretical strokes are not good production until efficiency, stock, die, setup, guarding, and controls are validated.","platforms":["LinkedIn","YouTube"],"asset":"PRESS_TOOL_REQUIRED","publishAllowed":false},
    {"day":21,"theme":"Customer privacy","draft":"Only the information needed for the agreed scope should enter the workflow.","platforms":["Facebook","Instagram","LinkedIn","Google Business Profile"],"asset":"PRIVACY_CARD_REQUIRED","publishAllowed":false},
    {"day":22,"theme":"Customer portal truth","draft":"Customer access is not called live until authentication, record isolation, file authorization, and replay tests pass.","platforms":["LinkedIn"],"asset":"SECURITY_STATUS_CARD_REQUIRED","publishAllowed":false},
    {"day":23,"theme":"Business OS productization","draft":"The Core Engine owns controls; the Business Pack owns terminology, catalog, templates, and workflow defaults.","platforms":["LinkedIn","YouTube"],"asset":"CORE_PACK_DIAGRAM_REQUIRED","publishAllowed":false},
    {"day":24,"theme":"Project sequence","draft":"A good project packet makes decision gates visible before purchases and installation.","platforms":["Facebook","Instagram","Google Business Profile"],"asset":"PROJECT_SEQUENCE_REQUIRED","publishAllowed":false},
    {"day":25,"theme":"Shop Flow Scorecard","draft":"Score travel, access, staging, incoming work, material, finished work, visual status, and cleanup.","platforms":["Facebook","Instagram","LinkedIn"],"asset":"SCORECARD_SCREENSHOT_REQUIRED","publishAllowed":false},
    {"day":26,"theme":"Robot readiness","draft":"Stable parts, interfaces, workholding, inspection, exceptions, safety, maintenance, and volume all matter.","platforms":["LinkedIn","YouTube"],"asset":"ROBOT_SCORECARD_REQUIRED","publishAllowed":false},
    {"day":27,"theme":"No fake completion","draft":"A feature is live only when its route, connection, test evidence, rollback point, and operating status are real.","platforms":["Facebook","Instagram","LinkedIn"],"asset":"QA_CARD_REQUIRED","publishAllowed":false},
    {"day":28,"theme":"Selected-record execution","draft":"The selected customer, job, quote, invoice, or post must be visible before action.","platforms":["LinkedIn","YouTube"],"asset":"SELECTED_RECORD_DEMO_REQUIRED","publishAllowed":false},
    {"day":29,"theme":"Start small","draft":"Use the smallest useful product, tool, or decision packet before expanding scope.","platforms":["Facebook","Instagram","Google Business Profile"],"asset":"CUSTOMER_PATH_CARD_REQUIRED","publishAllowed":false},
    {"day":30,"theme":"Highway 38 ecosystem","draft":"Solutions, Tools, Business OS, and future Supply Co. connect through one controlled operating system.","platforms":["Facebook","Instagram","LinkedIn","Google Business Profile","YouTube"],"asset":"ECOSYSTEM_OVERVIEW_REQUIRED","publishAllowed":false}
  ]
}
